pamphlet_detector/__init__.py
pamphlet_detector/main.py
pamphlet_detector-1.0.0.dist-info/METADATA
pamphlet_detector-1.0.0.dist-info/WHEEL
pamphlet_detector-1.0.0.dist-info/entry_points.txt
pamphlet_detector-1.0.0.dist-info/top_level.txt
pamphlet_detector-1.0.0.dist-info/RECORD
